aoc_cli_deno/__init__.py
aoc_cli_deno/getter.py
aoc_cli_deno/initialiser.py
aoc_cli_deno/language.py
aoc_cli_deno/local_validations.py
aoc_cli_deno/opener.py
aoc_cli_deno/runner.py
aoc_cli_deno/submitter.py
aoc_cli_deno-0.0.4.dist-info/LICENSE
aoc_cli_deno-0.0.4.dist-info/METADATA
aoc_cli_deno-0.0.4.dist-info/WHEEL
aoc_cli_deno-0.0.4.dist-info/entry_points.txt
aoc_cli_deno-0.0.4.dist-info/top_level.txt
aoc_cli_deno-0.0.4.dist-info/RECORD
