Metadata-Version: 2.1
Name: aoc-cli-deno
Version: 0.0.4
Summary: Advent of Code scaffolding CLI Deno plugin
Author-email: Emil Kloeden <emilkloeden@gmail.com>
Project-URL: Homepage, https://github.com/emilkloeden/aoc-cli-deno
Project-URL: Bug Tracker, https://github.com/emilkloeden/aoc-cli-deno/issues
Classifier: Programming Language :: Python :: 3
Classifier: License :: OSI Approved :: MIT License
Classifier: Operating System :: OS Independent
Requires-Python: >=3.10
License-File: LICENSE
Requires-Dist: aoc-cli-core (==0.0.2)
